build/lib/build/lib/build/lib/build/lib/build/lib/cwafcli/__init__.py
build/lib/build/lib/build/lib/build/lib/build/lib/cwafcli/__main__.py
build/lib/build/lib/build/lib/build/lib/build/lib/cwafcli/_version.py
build/lib/build/lib/build/lib/build/lib/build/lib/cwafcli/test_incap_cli.py
build/lib/build/lib/build/lib/build/lib/build/lib/cwafcli/Accounts/__init__.py
build/lib/build/lib/build/lib/build/lib/build/lib/cwafcli/Accounts/account.py
build/lib/build/lib/build/lib/build/lib/build/lib/cwafcli/Accounts/account_audit.py
build/lib/build/lib/build/lib/build/lib/build/lib/cwafcli/Accounts/cAccount.py
build/lib/build/lib/build/lib/build/lib/build/lib/cwafcli/Accounts/rAccount.py
build/lib/build/lib/build/lib/build/lib/build/lib/cwafcli/Accounts/rAccounts.py
build/lib/build/lib/build/lib/build/lib/build/lib/cwafcli/Accounts/rAudit.py
build/lib/build/lib/build/lib/build/lib/build/lib/cwafcli/Accounts/rSubAccounts.py
build/lib/build/lib/build/lib/build/lib/build/lib/cwafcli/Accounts/sub_account.py
build/lib/build/lib/build/lib/build/lib/build/lib/cwafcli/Accounts/subscription.py
build/lib/build/lib/build/lib/build/lib/build/lib/cwafcli/Config/__init__.py
build/lib/build/lib/build/lib/build/lib/build/lib/cwafcli/Config/configuration.py
build/lib/build/lib/build/lib/build/lib/build/lib/cwafcli/InfraProtect/__init__.py
build/lib/build/lib/build/lib/build/lib/build/lib/cwafcli/InfraProtect/testAlerts.py
build/lib/build/lib/build/lib/build/lib/build/lib/cwafcli/Integration/__init__.py
build/lib/build/lib/build/lib/build/lib/build/lib/cwafcli/Integration/clapps.py
build/lib/build/lib/build/lib/build/lib/build/lib/cwafcli/Integration/exception.py
build/lib/build/lib/build/lib/build/lib/build/lib/cwafcli/Sites/__init__.py
build/lib/build/lib/build/lib/build/lib/build/lib/cwafcli/Sites/acl.py
build/lib/build/lib/build/lib/build/lib/build/lib/cwafcli/Sites/cIncapRule.py
build/lib/build/lib/build/lib/build/lib/build/lib/cwafcli/Sites/cSite.py
cwaf_cli-2.2.18.dist-info/LICENSE.md
cwaf_cli-2.2.18.dist-info/METADATA
cwaf_cli-2.2.18.dist-info/WHEEL
cwaf_cli-2.2.18.dist-info/entry_points.txt
cwaf_cli-2.2.18.dist-info/top_level.txt
cwaf_cli-2.2.18.dist-info/RECORD
