Metadata-Version: 2.1
Name: cwaf-cli
Version: 2.2.18
Summary: Command-line used to interact with Imperva's Cloud-WAF
Home-page: https://github.com/imperva/incapsula-cli
Author: Joe Moore
Author-email: joe.moore@imperva.com
License: Imperva-Community Developer License
Platform: UNKNOWN
Classifier: License :: OSI Approved :: MIT License
Classifier: Programming Language :: Python :: 3.6
Classifier: Programming Language :: Python :: 3.7
Requires-Python: >=3.6
Requires-Dist: requests
